windows_tools-2.5.0-py3.12-nspkg.pth
windows_tools/antivirus/__init__.py
windows_tools/bitlocker/__init__.py
windows_tools/bitness/__init__.py
windows_tools/file_utils/__init__.py
windows_tools/impersonate/__init__.py
windows_tools/installed_software/__init__.py
windows_tools/logical_disks/__init__.py
windows_tools/misc/__init__.py
windows_tools/office/__init__.py
windows_tools/powershell/__init__.py
windows_tools/product_key/__init__.py
windows_tools/registry/__init__.py
windows_tools/securityprivilege/__init__.py
windows_tools/server/__init__.py
windows_tools/signtool/__init__.py
windows_tools/updates/__init__.py
windows_tools/users/__init__.py
windows_tools/virtualization/__init__.py
windows_tools/windows_firewall/__init__.py
windows_tools/wmi_queries/__init__.py
windows_tools-2.5.0.dist-info/LICENSE
windows_tools-2.5.0.dist-info/METADATA
windows_tools-2.5.0.dist-info/WHEEL
windows_tools-2.5.0.dist-info/namespace_packages.txt
windows_tools-2.5.0.dist-info/top_level.txt
windows_tools-2.5.0.dist-info/RECORD
