Metadata-Version: 2.1
Name: windows_tools
Version: 2.5.0
Summary: Toolset for antivirus, NTFS/ReFS ACLs, file ownership, registry, user handling...Well a lot of stuff
Home-page: https://github.com/netinvent/windows_tools
Author: NetInvent - Orsiris de Jong
Author-email: contact@netinvent.fr
License: BSD
Keywords: wmi,virtualization,file,acl,ntfs,refs,antivirus,security,firewall,office
Classifier: Development Status :: 5 - Production/Stable
Classifier: Intended Audience :: Developers
Classifier: Topic :: Software Development
Classifier: Topic :: System
Classifier: Topic :: System :: Operating System
Classifier: Topic :: System :: Shells
Classifier: Programming Language :: Python
Classifier: Programming Language :: Python :: 3
Classifier: Programming Language :: Python :: Implementation :: CPython
Classifier: Programming Language :: Python :: Implementation :: PyPy
Classifier: Operating System :: Microsoft
Classifier: Operating System :: Microsoft :: Windows
Classifier: License :: OSI Approved :: BSD License
Requires-Python: >=3.5
License-File: LICENSE
Requires-Dist: command-runner >=1.2.1
Requires-Dist: ofunctions.file-utils >=1.0.2
Requires-Dist: ofunctions.network >=1.3.2
Requires-Dist: ofunctions.json-sanitize >0.1.1
Requires-Dist: wmi >=1.4.9
Requires-Dist: psutil >=5.6.0
Requires-Dist: pywin32 >=210
Requires-Dist: typing >=3.5.0
Requires-Dist: python-dateutil >=2.8.1
